setup.py
pas_sdk_python3/__init__.py
pas_sdk_python3/pas_od.py
pas_sdk_python3.egg-info/PKG-INFO
pas_sdk_python3.egg-info/SOURCES.txt
pas_sdk_python3.egg-info/dependency_links.txt
pas_sdk_python3.egg-info/requires.txt
pas_sdk_python3.egg-info/top_level.txt