Metadata-Version: 1.2
Name: pas-sdk-python3
Version: 1.0.2
Summary: parametrix api service sdk for python3
Home-page: UNKNOWN
Author: Chaocanshu
Maintainer-email: 
License: Apache License 2.0
Platform: any
Classifier: Development Status :: 5 - Production/Stable
Classifier: Intended Audience :: Developers
Classifier: License :: OSI Approved :: Apache Software License
Classifier: Programming Language :: Python :: 3
Classifier: Programming Language :: Python :: 3.6
Classifier: Programming Language :: Python :: 3.7
Classifier: Programming Language :: Python :: 3.8
Classifier: Programming Language :: Python :: 3.9
